mrtautopilot/__init__.py
mrtautopilot/autopilot.py
mrtautopilot/mission.py
mrtautopilot-14.dist-info/METADATA
mrtautopilot-14.dist-info/WHEEL
mrtautopilot-14.dist-info/top_level.txt
mrtautopilot-14.dist-info/RECORD
