Metadata-Version: 2.1
Name: mrtautopilot
Version: 14
Summary: Communicate with the MRT Autopilot Mavlink API
Maintainer-email: Nathan Knotts <nathan@magothyrt.com>
Project-URL: Homepage, https://www.magothyrt.com/
Project-URL: Repository, https://github.com/magothy/mrtautopilot-py3.git
Requires-Python: >=3.8
Requires-Dist: mrtmavlink >=27.0
Requires-Dist: mrtproto >=16.0
Requires-Dist: zstandard >=0.23.0
